{
	"Name": "Bladetail Sturgeon",
	"Description": "(สเตอร์เจียนหางดาบ) เป็นปลาที่อันตรายสุดๆ หางของมันคมดั่งใบมีด การล่าพวกมันมากเกิน ไปทำให้จำนวนประชากร ของสายพันธุ์นี้ลดน้อยลง หางของพวกมัน เคยเป็นหัวลูกศร ในสมัยโบราณ",
	"Category": "Fish",
	"Edibility": 10,
	"EdibleIsDrink": false,
	"EdibleBuffs": null,
	"Price": 300,
	"IsColored": false,
	"GiftTastes":
	{
		"Love": ["Corine"],
	},

    "NameLocalization":
    {
    	//remove the "//" from your language
        //"es": "PLACEHOLDER",
        //"ko": "PLACEHOLDER",
        //"de": "PLACEHOLDER",
        //"fr": "PLACEHOLDER",
        //"hu": "PLACEHOLDER",
        //"it": "PLACEHOLDER",
        //"ja": "PLACEHOLDER",
        //"pt": "PLACEHOLDER",
        //"ru": "PLACEHOLDER",
        //"tr": "PLACEHOLDER",
        //"zh": "PLACEHOLDER",
    },
    "DescriptionLocalization":
    {
    	//remove the "//" from your language
        //"es": "PLACEHOLDER",
        //"ko": "PLACEHOLDER",
        //"de": "PLACEHOLDER",
        //"fr": "PLACEHOLDER",
        //"hu": "PLACEHOLDER",
        //"it": "PLACEHOLDER",
        //"ja": "PLACEHOLDER",
        //"pt": "PLACEHOLDER",
        //"ru": "PLACEHOLDER",
        //"tr": "PLACEHOLDER",
        //"zh": "PLACEHOLDER",
    }
}
