{
    "Changes": [
        {
            "Action": "EditData",
            "Target": "Characters/Dialogue/Abigail",
            "Entries":
            {
                "breakUp": " ...นั่นสินะ เธอคงไม่คิดว่าเราควรจะสนิทกันขนาดนั้น...$s#$b#ฉันว่าเราคงไม่เหมาะกันจริงๆหรอก...$s",
                "Thu10": "ตั้งแต่เธอย้ายมาที่นี่ก็ดูสดใสขึ้นเยอะเลยนะ$h#$b#เธอทำให้คนหลายๆคนมีชีวิตชีวาขึ้นเยอะเลย",
                "summer_Thu10": "ว้าววันนี้เธอดูดีจังเลยนะ#$e#ลมอุ่นๆตอนหน้าร้อนนี่ดีต่อผิวมากเลยล่ะ คิดเหมือนกันมั้ย?$h",
                "fall_Mon8": "รู้มั้ยบางทีอะฉันคิดว่าในอนาคตฉันอาจจะเป็นชาวไร่ก็ได้นะ...#$e#เธอคิดจะหาคนมาช่วยที่ฟาร์มบ้างมั้ยล่ะ @? *ฮ่า*$h",
                "fall_Fri10": "ปกติช่วงท้ายปีแบบนี้ฉันจะเหงามากๆเลย แต่มาตอนนี้ไม่แล้วล่ะ#$e#นี่ @ คิดว่าอนาคตจะทำอะไรต่อหรอ?",
                "winter_Fri10": "@ ฉันมีเรื่องจะคุยด้วย...ฉันคิดว่าเธอยอดมากเลยนะที่ยอมเสี่ยงย้ายมาที่นี่$6#$b#เธอมีงานประจำอยู่แล้วแถมการมาทำฟาร์มที่นี่ใช่ว่าจะสำเร็จด้วยแต่เธอก็ยังเลือกที่จะมา#$b#ต..แต่อย่าไปบอกใครนะว่าฉันคุยเรื่องนี้กับเธอ!$h",
                "fall_Thu10": "นี่เมื่อคืนฉันฝันถึงเธอด้วยนะ#$e#ตอนนั้นเรากำลังสู้กับพวกสัตว์ประหลาดล่ะ!$h",
                "Event_Cave_2": "ฉันคิดว่าเวลาที่เธอกำลังจะเสียอะไรไปแล้วรู้สึกกลัวมันก็เป็นเรื่องปกตินะ...$s",
                "NPC.cs.3980": "...!!! ธ...เธออยากจะใช้ชีวิตร่วมกันกับฉันหรอ?$7#$b#ในสถานะ {{RelationshipLabel}}? ฉ...ฉันตกลง!!นะ @!$h#$b#มันจะต้องเป็นอะไรที่แปลกใหม่แน่ๆเลย...การที่ทำอะไรแปลกใหม่แบบนี้เหมือนที่ฉันฝันมาตลอดเลยล่ะ!#$b#ที่นี่เราจะจัดงานแบบเหมือนงานแต่งเลยนะเดี๋ยวฉันจะไปเตรียมทุกอย่างให้พร้อมภายในสามวันหลังจากนี้นะ?$n",
                "NPC.cs.3962": "ว้าว @ เธอนี่รู้ใจฉันจริงๆ$h#$e#ฉันก็อยากรู้เรื่องของเธอเหมือนกันเพราะเธอคือเพื่อนที่ดีที่สุด$h",
                "NPC.cs.3963": "เธออยากจะเป็นเพื่อนสนิทกับฉันหรอฉันก็อยากเป็นนะ!$h#$e#ฉันกังวลนิดหน่อยน่ะกลัวว่าตอนเธอรู้ความลับแย่ๆของฉันแล้วเธอจะยังเป็นเพื่อนกับฉันอยู่มั้ย?",
                "NPC.cs.3985": "วันนี้ฉันได้ยินมาว่าเธอให้ของขวัญใครมานิ#$e#เธอนี่ใจดีจังเลยนะ!$h",
                "NPC.cs.4425": "ชีวิตเปลี่ยนไปมากเลยนะตั้งแต่เราเป็น {{RelationshipLabel}}...$s",
                "NPC.cs.4001": "ฉันเจอผลไม้นี่อยู่ในเหมืองน่ะ!$h#$b#ฉันให้เธอในฐานะที่เราเป็นครอบครัวเดียวกันแล้วและฉันจะสนับสนุนทุกสิ่งที่เธอทำนะ @.$n",
                "NPC.cs.4507": "@",
                "NPC.cs.4508": "@",
                "NPC.cs.4509": "@",
                "NPC.cs.4510": "@",
                "NPC.cs.4511": "@",
                "NPC.cs.4512": "{{TermofEndearment}}",
                "NPC.cs.4513": "{{TermofEndearment}}",
                "NPC.cs.4514": "{{TermofEndearment}}",
                "NPC.cs.4515": "{{TermofEndearment}}",
                "NPC.cs.4516": "{{TermofEndearment}}",
                "NPC.cs.4517": "Pal",
                "NPC.cs.4518": "Pal",
                "NPC.cs.4519": "Bud",
                "NPC.cs.4522": "Bud",
                "NPC.cs.4523": "Bud",
                "Event.cs.1736": "$q -1 null#ว่าไง?#$r -1 0 danceAsk#(ถามอบิเกลว่าจะเป็นคู่เต้นรำมั้ย)#$r -1 0 null#ไม่มีอะไรหรอก...",
            },
        },
        {
            "Action": "EditData",
            "Target": "Characters/Dialogue/Abigail",
            "Entries":
            {
                "NPC.cs.3965": "ฮืม..เธอเคยให้อันนี้ฉันแล้วนี่นา!$h",
                "NPC.cs.3966": "เธอก็รู้นิว่าฉันมีมันแล้วฮ่า!$h",
                "NPC.cs.3967": "ฉันก็อยู่กับเธอแล้วนี่ไง!$h",
                "NPC.cs.3968": "ฉันไม่ต้องการมันอีกเป็นชิ้นที่สองหรอกนะฮ่า!$h",
            },
            "When":
            {
                "Relationship:Abigail": "Engaged, Married"
            }
        },
        {
            "Action": "EditData",
            "Target": "Characters/Dialogue/Pierre",
            "Entries":
            {
                "NPC.cs.3965": "มันมีหลายเหตุผลที่ว่าทำไมครอบครัวฉันจะไม่ย้ายไปที่ฟาร์มของเธอ$3",
                "NPC.cs.3966": "อบิเกลไม่ต้องการให้ฉันมาหนุนหลังแล้วล่ะตอนนี้ถึงเวลาที่เธอใช้ชีวิตของตัวเอง$2",
                "NPC.cs.3967": "มันมีหลายเหตุผลที่ว่าทำไมครอบครัวฉันจะไม่ย้ายไปที่ฟาร์มของเธอ$3",
                "NPC.cs.3968": "อบิเกลไม่ต้องการให้ฉันมาหนุนหลังแล้วล่ะตอนนี้ถึงเวลาที่เธอใช้ชีวิตของตัวเอง$2",
            },
            "When":
            {
                "Relationship:Abigail": "Engaged, Married"
            }
        },
        {
            "Action": "EditData",
            "Target": "Characters/Dialogue/Caroline",
            "Entries":
            {
                "NPC.cs.3965": "ฉันไม่ต้องคอยอยู่กับแอ๊บบี้ไปตลอดหรอกเพราะฉันรู้ดีว่าเธอจะสบายดีแน่ถ้าอยู่กับเธอ",
                "NPC.cs.3966": "ให้ย้ายไปอยู่กับแอ๊บบี้หรอ? ...ค่อยมาถามฉันอีกทีตอนฉันกลายเป็นกระจกแล้วนะฮ่าๆ$2",
                "NPC.cs.3967": "ฉันไม่ต้องคอยอยู่กับแอ๊บบี้ไปตลอดหรอกเพราะฉันรู้ดีำว่าเธอจะสบายดีแน่ถ้าอยู่กับเธอ",
                "NPC.cs.3968": "ให้ย้ายไปอยู่กับแอ๊บบี้หรอ? ...ค่อยมาถามฉันอีกทีตอนฉันกลายเป็นกระจกแล้วนะฮ่าๆ$2",
            },
            "When":
            {
                "Relationship:Abigail": "Engaged, Married"
            }
        },
        {
            "Action": "EditData",
            "Target": "Characters/Dialogue/Abigail",
            "Entries":
            {
                "NPC.cs.4442": "เมื่อเช้าฉันรู้สึกคลื่นไส้แปลกๆ...น่าจะเป็นเพราะเรื่องคำร้องขอจดทะเบียนรับบุตรบุญธรรมแน่ๆเลย...$s",
                "NPC.cs.4446": "วันนี้ฉันรู้สึกง่วงมากๆเลยแฮะ...น่าจะเป็นเพราะว่าฉันเอาแต่รอจดหมายทางอีเมล$s#$b#ฉันหวังว่าหน่วยงานรับเลี้ยงบุตรจะส่งอีเมลมาในเร็วๆนี้นะ",
                "NPC.cs.4443": "เหนื่อยจังเลย... ทำอาหารเช้ากินเองไปละกัน$s",
                "NPC.cs.4444": "{{TermofEndearment}}, ไม่อยากจะเชื่อเลยว่าเรากำลังจะได้รับเลี้ยงเด็กด้วยกันน่าจะเป็นอะไรที่สุดยอดมากๆเลย!$h",
                "NPC.cs.4447": "{{TermofEndearment}}, ไม่อยากจะเชื่อเลยว่าเรากำลังจะได้รับเลี้ยงเด็กด้วยกันน่าจะเป็นอะไรที่สุดยอดมากๆเลย!$h",
                "NPC.cs.4445": "{{TermofEndearment}}, ฉันคิดว่าการรับเลี้ยงเด็กจะต้องดีมากแน่ๆ",
                "NPC.cs.4448": "{{TermofEndearment}}, ฉันคิดว่าการรับเลี้ยงเด็กจะต้องดีมากแน่ๆ",
            },
            "When":
            {
                "EnableAsexuality": true,
            }
        },
        {
            "Action": "EditData",
            "Target": "Strings/StringsFromCSFiles",
            "Entries":
            {
                "Game1.cs.2782": "นั่นไม่ใช่เรื่องดีๆหรอ? ฉันว่าแต่งตัวให้พร้อมดีกว่านะ#$e#เอาล่ะ!เริ่มการผจญภัยครั้งใหม่ได้เลย!$h",
            },
            "When":
            {
                "Spouse": "Abigail"
            },
        },
        {
            "Action": "EditData",
            "Target": "Characters/Dialogue/MarriageDialogueAbigail",
            "Entries":
            {
                "Rainy_Night_5": "นี่?ฉันว่าเธอดูเหนื่อยๆนะมีอะไรที่ฉันพอจะช่วยได้มั้ย?$h",
                "Good_5": "ฉันกำลังนั่งดูสร้อยคอตอนที่เธอขอให้ฉันมาอยู่ด้วยอยู่ล่ะ... ฉันตั้งใจไว้ว่าจะเอาตั้งไว้หน้าหลุมศพของฉัน",
                "Neutral_0": "ฉันหวังว่าเธอจะยังรักฉันจนฉันแก่ตัวจนเอาของขวัญจากเหมืองมาให้เธอไม่ได้อีกแล้ว#$b#เดี๋ยววันนั้นมันก็จะมาถึงเองแหละ!",
                "Bad_9": "ฉันเคยเป็นเพื่อนรักกับเซบาสเตียนก่อนที่จะมาเจอเธอ ฉันน่าจะไปอยู่กับเขานะ...$s",
                "spring_12": "นี่!วันพรุ่งนี้ก็จะถึงเทศกาลไข่อีสเตอร์แล้วนะเธอเตรียมตัวรึยังแต่บอกไว้ก่อนนะถึงเราจะเป็นเพื่อนรักกันฉันก็จะไม่ออมมือให้หรอก!$h#$e#ฉันตั้งใจเอาไว้ว่าฉันจะต้องชนะไม่งั้นก็ลองเอาชนะฉันดูสิ!",
                "summer_1": "ฤดูนี้มาอีกแล้วหรอฉันยิ่งไม่ชอบโดนแดดเผาด้วยสิต้องระวังหน่อยแล้ว",
                "summer_4": "ระวังอย่าให้เป็นลมแดดซะล่ะ @#$e#ดื่มน้ำเยอะๆแล้วก็อย่าหักโหมนะ",
                "fall_2": "เรามาปลูกฟักทองยักษ์กันเถอะนะฉันขอละขอร้องนะ @?$h",
                "fall_20": "@... รู้มั้ยว่าสำหรับฉันแล้วเธอมีค่ามากกว่ากล่องที่เต็มไปด้วยแร่ต่างๆอีกนะ#$e#แต่ถ้ากล่องนั้นเต็มไปด้วยแร่แอเมทิสต์.. ฉันคงจะต้องคิดใหม่ละนะฮ่า$h",
            },
        },
        {
            "Action": "EditData",
            "Target": "Characters/Dialogue/MarriageDialogueAbigail",
            "Entries":
            {
                "Indoor_Night_Abigail": "รอไม่ไหวแล้วที่จะได้ไปนอนห่มผ้าห่มไฟฟ้า",
            },
            "When":
            {
                "EnableAsexuality": "true"
            },
        },
        {
            "Action": "EditData",
            "Target": "Characters/Dialogue/Sebastian",
            "Entries":
            {
                "Wed2_inlaw_Abigail": "แซมกับแอ๊บบี้เป็นเพื่อนเพียงกลุ่มเดียวของฉันในเมืองนี้แล้วละ#$e#แอ๊บบี้ค่อนข้างที่จะ... ที่จะแบบว่า... $h#$e#เอ่อ..ช่างมันเถอะเอาเป็นว่าอย่าไปบอกแอ๊บบี้ว่าฉันพูดถึงเธอนะ",
            },
        },
        {
            "Action": "EditData",
            "Target": "Characters/Dialogue/Caroline",
            "Entries":
            {
                "Mon_inlaw_Abigail": "ว่าไง @ เธอกับแอ๊บบี้มีความสุขดีมั้ยในฐานะ {{RelationshipLabel}}? ฉันก็หวังให้มีความสุขนะ!",
            },
        },
        {
            "Action": "EditData",
            "Target": "Characters/Dialogue/Pierre",
            "Entries":
            {
                "Mon_inlaw_Abigail": "ไง @ เดี๋ยวนี้เธอแอ๊บบี้เป็นไงกันบ้าง",
            },
        },
        {
            "Action": "EditData",
            "Target": "Data/EngagementDialogue",
            "Entries":
            {
                "Abigail0": "ฉันคนนี้เนี่ยนะ? ที่จะย้ายไปอยู่ฟาร์ม? ไม่เคยคิดเลยว่าจะเกิดขึ้น$h#$e#พวกเราจะต้องมีความสุขมากแน่ๆเลย$h",
                "Abigail1": "ฉันกำลังจะได้เป็น {{RelationshipLabel}} กับชาวไร่ด้วยล่ะ!$h#$e#ชีวิตเราจะต้องมีอะไรเกิดขึ้นมากมายแน่ๆ$n",
            },
        },
        {
            "Action": "EditData",
            "Target": "Data/ExtraDialogue",
            "Entries":
            {
                "SummitEvent_Dialogue3_Abigail": "ยืนอยู่ตรงนี้แล้วมองออกไปที่เส้นขอบฟ้า... ฉันรู้สึกเหมือนความรู้สึกมันพรั่งพรูออกมาไม่รู้จบเลย#$b#ฉันมีความสุขมากเลยที่ได้ออกผจญภัยกับเธอ",
            },
        },
        {
            "Action": "EditData",
            "Target": "Data/Festivals/winter8",
            "Entries":
            {
                "Abigail_spouse": "ไง @... ดูนี่มันเป็นของเธอนะ!$h",
            },
        },
        {
            "Action": "EditData",
            "Target": "Strings/StringsFromCSFiles",
            "Entries":
            {
                "Event.cs.1613": "ต...แต่...ฉันอยากจะเต้นกับ..$s#$b#ฮ่าล้อเล่นน่าฉันอยากเต้นกับเธออยู่แล้ว เพราะเธอคือคนพิเศษยังไงล่ะ!$h",
            },
        },
        {
            "Action": "EditData",
            "Target": "Data/Events/SeedShop",
            "Entries":
            {
                "3/f Abigail 2000/p Abigail/t 2000 2200/n abbySpiritBoard": "echos/-1000 -1000/farmer 13 6 3 Abigail 6 8 1/skippable/specificTemporarySprite abbyOuijaCandles/viewport 7 5/speak Abigail \"ฉันกำลังอยากให้เธอมาที่นี่พอดีเลยตามมาสิฉันมีอะไรจะให้เธอดู\"/move farmer -5 0 0/move farmer 0 2 3/faceDirection Abigail 2/speak Abigail \"เห็นนี่มั้ยเค้าเรียกว่ากระดานวิญญาณน่ะเคยใช้มาก่อนมั้ย?\"/emote farmer 8/move Abigail 0 2 1/move farmer 0 2 3/pause 500/speak Abigail \"เอามือเธอแตะที่ไม้กระดานนะ...\"/showFrame Abigail 30/pause 200/animate farmer true true 9999 89/pause 600/speak Abigail \"เอาล่ะทีนี้วิญญาณจะคอยนำเรานะ...$h\"/showFrame Abigail 31/pause 500/speak Abigail \"ดูสิ!มันขยับแล้ว!$7\"/emote farmer 16/speak Abigail \"ตัวอักษรแรกคือ... 'ต' ...\"/pause 600/speak Abigail \"ต่อไปคือ... 'า' ...\"/pause 800/speak Abigail \"ดูสิๆจะได้เป็นคำว่าอะไรนะ! อะนั้นไงๆ... 'ข'... 'า'... พวกขี้ขลาดตาข...?\"/emote Abigail 16/showFrame Abigail 12/faceDirection Abigail 3/stopMusic/pause 200/stopAnimation farmer/faceDirection Abigail 1/pause 400/specificTemporarySprite abbyOuija/playSound swordswipe/pause 900/playSound seeds/pause 500/speak Abigail \"โอ๊ะ เผลอทำกระดานหล่นซะได้! อิอิ...$h#$b#มันก็แค่เกมเล่นขำๆน่ะไม่ต้องไปสนใจหรอก$9\"/faceDirection Abigail 3/emote Abigail 28/faceDirection Abigail 1/speak Abigail \"อ..เอ่อคือฉันต้องไปแล้วนะลาก่อน$9\"/faceDirection Abigail 2/emote farmer 28/pause 500/move farmer 0 -3 0/pause 800/faceDirection farmer 2/pause 1000/move farmer 5 0 1 true/globalFade/viewport -1000 -1000/end invisibleWarpOut Abigail",
            },
        },
        {
            "Action": "EditData",
            "Target": "Data/Events/Farm",
            "Entries":
            {
                "5/e 3/v Abigail/t 600 800": "continue/64 15/farmer 64 16 2 Abigail 64 18 0/pause 1500/speak Abigail \"ไง..เอ่อคือ..ฉันแค่จะมาขอโทษเรื่องเมื่อวานที่ฉันทำตัวแปลกๆน่ะ$6#$b#เธอน่าจะเดาออกนะสำหรับเรื่องที่เกินขึ้นไอเจ้ากระดานวิญญาณนั่นทำให้ความจริงของฉันเปิดเผยออกมาก็นั่นแหละ...$6#$b#บางครั้งฉันก็คิดนะว่าฉันกำลังหลอกตัวเองอยู่รึเปล่า$s#$b#จำได้มั้ยที่ฉันชอบพูดว่าอยากทำอะไรที่มันน่าตื่นเต้นแบบไปลงเหมืองอะไรแบบนี้?$6#$bทำไมฉันต้องพูดอะไรแบบนี้ด้วยนะเหมือนกับแกว่งดาบไปทั่วๆเฉยๆอย่างงั้นแหละ?$u#$b#นี่ฉันอยากจะไปผจญภัยจริงๆรึเปล่านะหรือแค่แสร้งทำเฉยๆ...?$u#$b#...ขอโทษนะฉันไม่น่ามาทิ้งเรื่องนี้ไว้กับเธอเลย$s#$b#ว..ไว้เจอกันนะ$s\"/pause 500/end",
            },
        },
        {
            "Action": "EditData",
            "Target": "Data/Events/Mine",
            "Entries":
            {
                "901756/f Abigail 2500/t 1700 2400/o Abigail": "Upper_Ambient/18 7/farmer -1000 -1000 0 Abigail 18 11 0/skippable/move Abigail 0 -3 1/move Abigail 5 0 2/pause 500/animate Abigail false false 150 26 24 25 25 25 25/pause 450/playSound sandyStep/stopAnimation Abigail/showFrame Abigail 25/pause 2000/playSound batFlap/pause 500/playSound batFlap/pause 500/playSound batFlap/pause 500/emote Abigail 8/pause 1000/specificTemporarySprite abbyOneBat/playSound batScreech/showFrame Abigail 32/shake Abigail 2000/pause 2000/showFrame Abigail 0/pause 600/animate Abigail false true 100 28 29/pause 1200/stopAnimation Abigail/pause 1000/specificTemporarySprite abbyManyBats/showFrame Abigail 32/shake Abigail 2000/pause 2000/speed Abigail 8/move Abigail 0 -4 0/speed Abigail 8/move Abigail 2 0 0/animate Abigail false false 100 21 20 20/pause 200/showFrame Abigail 20/shake Abigail 10000/pause 2000/warp farmer 18 13/move farmer 0 -5 0/pause 1000/faceDirection farmer 1/pause 300/emote farmer 16/speed farmer 8/move farmer 6 0 0/speed farmer 8/playMusic desolate/move farmer 0 -4 1/speak Abigail \"$q 776589 null#*ฝืด*$s#$r 776589 20 Event_Cave2_1#เกิดอะไรขึ้นน่ะ?#$r 776589 40 Event_Cave2_2#เธอเป็นอะไรมั้ย?\"/pause 500/animate Abigail false false 100 21 0 0/pause 200/stopAnimation Abigail/faceDirection Abigail 3/pause 500/speak Abigail \"เธอรู้มั้ยว่าสักพักมานี้ฉันฝึกวิชาดาบมาตลอดเลย...$8#$b#และฉันก็ไม่ค่อยมั่นใจว่าจะฝึกต่อไปดีมั้ย?$8#$b#วันนี้ฉันก็เลยว่าจะลองมาที่ถ้ำดูล่ะ...$8\"/pause 500/faceDirection Abigail 1/pause 1000/speak Abigail \"...แต่ว่าฉันก็กลัวเกินกว่าจะเข้าไปอะสิ$s\"/pause 500/faceDirection Abigail 3/speak Abigail \"$q 34 null#บางทีฉันคงจะไม่กล้าพอเท่ากับที่ฉันหวังไว้...$8#$r 34 20 Event_Cave_1#เธอจะปลอดภัยถ้าอยู่กับฉัน#$r 34 40 Event_Cave_2#ฉันก็กลัวเหมือนกันแหละฮ่า#$r 34 -50 Event_Cave_3#หยุดร้องไห้ทำตัวเป็นเด็กสักทีเถอะ\"/faceDirection Abigail 3/stopMusic/pause 1500/playMusic sadpiano/pause 1800/speak Abigail \"@...เธอเป็นคนสำคัญของฉันจริงๆนะเธอรู้มั้ย?$8#$b#เธอเป็นเพื่อนที่ดีที่สุดของฉันและเธอก็ได้เห็นตัวตนที่จริงของฉันที่ไม่ใช่คนที่ฉันควรจะเป็นแบบที่ทุกคนอยากให้ฉันเป็น$8#$b#เธอเห็นว่าฉันอยากจะเป็นนักผจญภัยที่กล้าหาญและเธอก็เชื่อมั่นว่าฉันจะเป็นนักผจญภัยได้แน่นอน$8#$b#และนั่นก็ทำให้ฉันเชื่อมั่นในตัวเองเหมือนกัน$n\"/pause 2000/speak Abigail \"ฉันคิดว่ามันก็ไม่เป็นอะไรหรอกนะที่ฉันจะกลัวถ้ำพวกนี้เพราะถ้ามันไม่น่ากลัวมันก็คงจะไม่น่าตื่นเต้นหน่ะสิ!$h#$b#แต่ฉันจะต้องไปสำรวจมันแน่ๆถึงแม้ว่าจะไม่ใช่วันนี้ก็เถอะและถ้าฉันออกนอกลู่นอกทางอีกก็จะมีเธอคอยชี้นำฉันอยู่ตลอดยังไงล่ะ$n#$b#ขอบคุณจริงๆนะ @ ฉันดีใจจริงๆที่ได้เป็นเพื่อนกับเธอ\"/pause 1000/animate Abigail true true 100 30/positionOffset Abigail -8 0/positionOffset farmer 8 0/animate farmer false true 100 101/pause 2500/globalFade/viewport -1000 -1000/end",
            },
        },
        {
            "Action": "EditData",
            "Target": "Data/Events/Backwoods",
            "Entries":
            {
                "6963327/f Abigail 3500/O Abigail/t 610 1700": "continue/-100 -100/farmer 39 14 0 golem 37 15 0 Abigail -100 23 0/addWorldState golemGrave/makeInvisible 37 11 5 7/skippable/pause 1000/viewport 39 11 clamp true/move farmer 0 -3 0/doAction 39 10/pause 500/doAction 39 10/pause 1000/move farmer 1 0 0/playMusic none/pause 100/doAction 39 10/playSound rockGolemSpawn/move Golem 0 -4 0/doAction 39 10/move Golem 2 0 1/pause 500/faceDirection farmer 3/pause 300/playSound rockGolemHit/pause 100/faceDirection farmer 2 true/animate farmer false true 100 94/jump farmer/pause 700/showFrame Golem 5/specificTemporarySprite swordswipe 39 11/playSound swordswipe/pause 250/playSound hitEnemy/startJittering/positionOffset farmer 8 0/pause 20/positionOffset farmer 8 0/pause 20/positionOffset farmer 8 0/pause 20/positionOffset farmer 8 0/pause 20/positionOffset farmer 8 0/pause 20/positionOffset farmer 8 0/pause 20/positionOffset farmer 8 0/pause 20/positionOffset farmer 8 0/playSound clubhit/stopJittering/pause 20/showFrame Golem 4/showFrame farmer 5/pause 1000/move Golem 1 0 1/warp Abigail 49 14/animate Golem false true 150 4 5 6 7/move Abigail -5 0 3/jump Abigail/animate Abigail false true 100 32/speak Abigail \"*เฮือก*...!$7\"/stopAnimation Abigail/speed Abigail 8/move Abigail -5 0 0/speed Abigail 8/move Abigail 0 -3 1/pause 250/animate Abigail false false 200 50 51/specificTemporarySprite swordswipe 39 11/playSound swordswipe/pause 250/playSound rockGolemHit/stopAnimation Golem/shake Golem 250/faceDirection Golem 3 true/pause 500/animate Abigail false false 200 50 51/specificTemporarySprite swordswipe 39 11/playSound swordswipe/pause 250/playSound rockGolemHit/stopAnimation Golem/shake Golem 250/pause 250/animate Abigail false false 200 50 51/specificTemporarySprite swordswipe 39 11/playSound swordswipe/pause 250/playSound rockGolemDie/specificTemporarySprite golemDie/warp Golem -100 -100/pause 750/playMusic echos/speed Abigail 4/move Abigail 1 0 1/pause 700/animate Abigail false true 100 39/pause 100/emote Abigail 28/pause 400/speak Abigail \"@...?$6\"/pause 1000/speak Abigail \"@...เธอเป็นอะไรมั้ย?$6\"/pause 1500/startJittering/pause 500/stopJittering/pause 1000/startJittering/pause 500/stopJittering/pause 1000/stopAnimation farmer/showFrame farmer 0/jump farmer/pause 250/stopAnimation Abigail/showFrame Abigail 4/pause 500/faceDirection farmer 3/speak Abigail \"ดูเหมือนว่าเธอจะมีแผลถลอกนิดหน่อยนะ...เฮ้ออย่าทำให้ฉันเป็นห่วงสิ!\"/pause 450/animate Abigail false true 100 30/positionOffset Abigail 8 0/positionOffset farmer -8 0/animate farmer true true 100 101/pause 1500/positionOffset farmer 8 0/positionOffset Abigail -8 0/stopAnimation farmer/stopAnimation Abigail/showFrame Abigail 4/pause 1300/faceDirection Abigail 2/pause 800/move Abigail 0 1 2/faceDirection farmer 2/pause 500/move farmer 0 1 3/emote Abigail 28/pause 1200/speak Abigail \"ฉ..ฉันไม่เคยทำร้ายใครมาก่อนเลย...$s\"/pause 700/faceDirection Abigail 1/pause 550/quickQuestion #น่าเศร้านะแต่ว่ามันไม่มีทางเลือกอื่นแล้ว#พวกปีศาจหน่ะไม่ควรได้รับความเมตตาหรอกนะ!#โลกมันก็เป็นยังงี้แหละนะ#เธอจำเป็นต้องฆ่าเค้าด้วยหรอ?(break)speak Abigail \"ใช่แล้ว...ฉันควรทำในสิ่งที่ต้องทำ$s#$b#ฉันว่าโลกนี้ก็โหดร้ายสำหรับทุกคนแหละ ไม่ว่าจะเป็นเธอหรือเค้า?$6\"(break)speak Abigail \"...ไม่ใช่ว่าพวกเค้าก็พยายามเอาชีวิตรอดเหมือนพวกเราหรอกหรอ?$s#$b#ถึงแม้ว่าพวกเค้าจะเป็นศัตรูของเราแต่ว่าพวกเค้าก็ควรได้รับความเมตตาเหมือนกัน$6#$b#ฉันทำสิ่งที่ควรทำแล้วล่ะ$6\"(break)speak Abigail \"เห..คำพูดแบบนั้นออกมาจากคนที่พึ่งโดนช่วยมานี่น่าตลกจัง...$h#$b#บางครั้งความเป็นจริงจะบังคับเราให้ทำในสิ่งที่ผิด...นี่เป็นบทเรียนนึงที่ยากพอตัวเลยแหะ$6\"(break)speak Abigail \"นี่!ฉันพึ่งช่วยชีวิตเธอไว้อย่าลืมพาฉันไปเที่ยวบ้างละ!$a\"\\pause 600/pause 500/emote Abigail 40/pause 500/speak Abigail \"ฟังนะ..คราวหลังเธอต้องระวังตัวให้มากกว่านี้นะฉันไม่อยากเสียเธอไป\"/pause 500/animate Abigail false true 100 30/positionOffset Abigail 8 0/positionOffset farmer -8 0/animate farmer true true 100 101/pause 2000/positionOffset farmer 8 0/positionOffset Abigail -8 0/stopAnimation farmer/stopAnimation Abigail/showFrame Abigail 4/pause 1300/faceDirection Abigail 2/faceDirection farmer 2/pause 500/animate Abigail false true 100 0 1 2 3/positionOffset Abigail 0 2/pause 50/positionOffset Abigail 0 2/pause 50/positionOffset Abigail 0 2/pause 50/positionOffset Abigail 0 2/pause 50/positionOffset Abigail 0 2/pause 50/positionOffset Abigail 0 2/pause 50/positionOffset Abigail 0 2/pause 50/positionOffset Abigail 0 2/pause 50/positionOffset Abigail 0 2/pause 50/positionOffset Abigail 0 2/pause 50/positionOffset Abigail 0 2/pause 50/positionOffset Abigail 0 2/pause 50/positionOffset Abigail 0 2/pause 50/stopAnimation Abigail/pause 500/showFrame Abigail 26/pause 100/showFrame Abigail 27/pause 600/speak Abigail \"เราพาเค้าไปฝังกันเถอะนะ.. okay?$6\"/pause 600/fade/viewport -1000 -1000/pause 1000/playSound dirtyHit/pause 600/playSound dirtyHit/pause 600/playSound dirtyHit/pause 600/playSound dirtyHit/pause 2000/end dialogue Abigail \"แต่โชคดีนะเนี่ยที่วันนี้ฉันเอาดาบมาด้วย!$6\"",
            },
        },
        {
            "Action": "EditImage",
            "Target": "Characters/Abigail",
            "FromFile": "assets/Sprites/AbigailDressRecolor.png",
            "ToArea":
            {
                "X": 0,
                "Y": 293,
                "Width": 45,
                "Height": 27
            },
            "PatchMode": "Overlay",
            "When":
            {
                "EnableSpriteEdits": true,
                "HasMod |contains=DSVTeam.DiverseSeasonalOutfits": "false",
                "HasMod |contains=DSVTeam.DSVNonSeasonal": "false",
            },
        },
        {
            "Action": "EditImage",
            "Target": "Portraits/Abigail",
            "FromFile": "assets/Portraits/AbigailNoBlush.png",
            "ToArea":
            {
                "X": 0,
                "Y": 0,
                "Width": 128,
                "Height": 320
            },
            "PatchMode": "Overlay",
            "When":
            {
                "EnablePortraitEdits": true,
                "HasMod |contains=DSVTeam.DiverseSeasonalOutfits": "false",
                "HasMod |contains=DSVTeam.DSVNonSeasonal": "false",
                "HasMod |contains=Poltergeister.SeasonalCuteCharacters": "false",
            },
        },
        //COMPATIBILITY: SEASONAL OUTFITS - SLIGHTLY CUTER AESTHETIC
        //This section uses (with permission) overlays copied from Poltergeister's portrait assets to implement blush edits compatible with Seasonal Cute Characters. (Thank you, Poltergeister!)
        {
            "Action": "EditImage",
            "Target": "Portraits/Abigail",
            "FromFile": "assets/Portraits/AbigailNoBlush_SeasonalCuteCharacters.png",
            "ToArea":
            {
                "X": 0,
                "Y": 0,
                "Width": 128,
                "Height": 320
            },
            "PatchMode": "Overlay",
            "When":
            {
                "EnablePortraitEdits": true,
                "HasMod |contains=DSVTeam.DiverseSeasonalOutfits": "false",
                "HasMod |contains=DSVTeam.DSVNonSeasonal": "false",
                "HasMod |contains=Poltergeister.SeasonalCuteCharacters": "true",
            },
        },
        //COMPATIBILITY: PLATONIC RELATIONSHIPS
        //This section prevents the dating-flag-required version of the vanilla 10 heart event added by Platonic Relationships from triggering. Thanks to Cherry for providing the event codes!
        {
            "Action": "EditData",
            "Target": "Data/Events/Mine",
            "Entries":
            {
                "901756/f Abigail 2500/D Abigail/t 1700 2400/o Abigail": null,
            },
            "When":
            {
                "HasMod |contains=Cherry.PlatonicRelationships": "true"
            },
        },
        //COMPATIBILITY: CANON-FRIENDLY DIALOGUE EXPANSION FOR ALL FRIEND-ABLE CHARACTERS v2.0.2
        //Lines in this section are based on the original lines written by gizzymo, used and edited with permission. (Thank you, gizzymo!)
        {
            "Action": "EditData",
            "Target": "Characters/Dialogue/Abigail",
            "Entries":
            {
                "Fri8": "ฉันเคยคิดเล่นๆนะว่าบางทีตอนเราตื่นมาเรื่องทั้งหมดที่เกินมาจนถึงตอนนี้เป็นเพียงแค่ความฝัน$6#$e#แต่พอได้มาเจอเธอก็ไม่อยากให้มันเป็นแบบนั้นแล้วละ",
                "Sat6": "นี่เธอตั้งใจมาหาฉันหรอรู้สึกดีจัง!$h#$e#แล้วเธอได้สำรวจถ้ำที่ภูเขาจนทั่วรึยังล่ะ?#$e#น่าสนใจดีนะ ฉันหวังว่าสักวันฉันจะไปที่นั่นได้",
                "Sat10": "แต่ก่อนฉันก็คิดว่าการตายไปก็คงจะดีนะไม่มีอะไรต้องห่วงแต่ว่าตอนนี้คงต้องคิดใหม่แล้วละ#$b#เพราะฉันไม่อยากทิ้งเธอไว้ข้างหลังไง$l",
                "summer_Sat10": "นี่อาจจะเป็นหน้าร้อนที่ดีที่สุดสำหรับฉันเลยละ$h#$e#แต่ว่าคิดเรื่องได้ใช้เวลากับเธอตอนฤดูใบไม้ร่วงมาถึงก็ฟังดูน่าสนใจมากๆเลย$l",
                "fall_Thu8": "ฉันเคยคิดเล่นๆนะว่าบางทีตอนเราตื่นมาเรื่องทั้งหมดที่เกินมาจนถึงตอนนี้เป็นเพียงแค่ความฝัน$6#$e#แต่พอได้มาเจอเธอก็ไม่อยากให้มันเป็นแบบนั้นแล้วละ",
                "winter_Tue10": "*กอด* ไง!$h#$e#ฉันไม่ได้กอดเธอเพราะหนาวหรอกนะแต่กอดเพราะว่าเธอน่ารักยังไงละ!$h",
                "winter_Fri8": "เธอเคยคิดมั้ยว่าสิ่งที่เธอทุ่มเททำกันมันไปมันไม่ได้เกิดประโยชน์อะไรเลย?$s#$e#ฉ..ฉันหมายถึงเฮ้อช่างมันเถอะอย่าไปใส่ใจหรอกฉันก็พูดไปงั้นแหละ$h",
                "winter_Sat10": "ขอบคุณนะที่ไม่ล้อฉันเกี่ยวกับเรื่องกระดานวิญญาณตอนนั้น$6#$e#มันน่าอายมากๆเลยที่ความลับถูกเปิดเผยยังงั้น$s",
                "winter_Sun10": "นี่ถ้าเธออยากจะมาหาฉันที่ห้องก็มาได้เลยนะ#$e#เธอไม่ต้องกังวลนะเพราะฉันรอที่จะเจอเธออยู่ตลอดเลย",
            },
            "When":
            {
                "UseLovePortraits": true,
                "HasMod |contains=gizzymo.canonfriendlyexpansion": "true"
            },
        },
        {
            "Action": "EditData",
            "Target": "Characters/Dialogue/Abigail",
            "Entries":
            {
                "Fri8": "ฉันเคยคิดเล่นๆนะว่าบางทีตอนเราตื่นมาเรื่องทั้งหมดที่เกินมาจนถึงตอนนี้เป็นเพียงแค่ความฝัน$6#$e#แต่พอได้มาเจอเธอก็ไม่อยากให้มันเป็นแบบนั้นแล้วละ",
                "Sat6": "นี่เธอตั้งใจมาหาฉันหรอรู้สึกดีจัง!$h#$e#แล้วเธอได้สำรวจถ้ำที่ภูเขาจนทั่วรึยังล่ะ?#$e#น่าสนใจดีนะ ฉันหวังว่าสักวันฉันจะไปที่นั่นได้",
                "Sat10": "แต่ก่อนฉันก็คิดว่าการตายไปก็คงจะดีนะไม่มีอะไรต้องห่วงแต่ว่าตอนนี้คงต้องคิดใหม่แล้วละ#$b#เพราะฉันไม่อยากทิ้งเธอไว้ข้างหลังไง$6",
                "summer_Sat10": "นี่อาจจะเป็นหน้าร้อนที่ดีที่สุดสำหรับฉันเลยละ$h#$e#แต่ว่าคิดเรื่องได้ใช้เวลากับเธอตอนฤดูใบไม้ร่วงมาถึงก็ฟังดูน่าสนใจมากๆเลย",
                "fall_Thu8": "ฉันเคยคิดเล่นๆนะว่าบางทีตอนเราตื่นมาเรื่องทั้งหมดที่เกินมาจนถึงตอนนี้เป็นเพียงแค่ความฝัน$6#$e#แต่พอได้มาเจอเธอก็ไม่อยากให้มันเป็นแบบนั้นแล้วละ",
                "winter_Tue10": "*กอด* ไง!$h#$e#ฉันไม่ได้กอดเธอเพราะหนาวหรอกนะแต่กอดเพราะว่าเธอน่ารักยังไงละ!$h",
                "winter_Fri8": "เธอเคยคิดมั้ยว่าสิ่งที่เธอทุ่มเททำกันมันไปมันไม่ได้เกิดประโยชน์อะไรเลย?$s#$e#ฉ..ฉันหมายถึงเฮ้อช่างมันเถอะอย่าไปใส่ใจหรอกฉันก็พูดไปงั้นแหละ$h",
                "winter_Sat10": "ขอบคุณนะที่ไม่ล้อฉันเกี่ยวกับเรื่องกระดานวิญญาณตอนนั้น$6#$e#มันน่าอายมากๆเลยที่ความลับถูกเปิดเผยยังงั้น$s",
                "winter_Sun10": "นี่ถ้าเธออยากจะมาหาฉันที่ห้องก็มาได้เลยนะ#$e#เธอไม่ต้องกังวลนะเพราะฉันรอที่จะเจอเธออยู่ตลอดเลย",
            },
            "When":
            {
                "UseLovePortraits": false,
                "HasMod |contains=gizzymo.canonfriendlyexpansion": "true"
            },
        },
        {
            "Action": "EditData",
            "Target": "Characters/Dialogue/MarriageDialogueAbigail",
            "Entries":
            {
                "Rainy_Day_0": "#$c .5#ฉันว่าวันนี้จะเอาสมุดสเก็ตช์ออกมาปัดฝุ่นหน่อยละนะเพราะพึ่งได้ไอเดียสัตว์ในเทพนิยายมา#ความมืด... สายฝน... มันทำให้ฉันตื่นเต้นอย่างบอกไม่ถูกเลยละ$h",
                "Rainy_Day_1": "นี่ๆจำตอนนั้นได้มั้ยตอนที่ฝนตกลงมาแล้วเราก็เล่นเพลงด้วยกันพอฝนตกแบบนี้ก็ทำให้ย้อนคิดขึ้นมาน่ะ#$e#$c .5#เธอยังพกพิณอยู่กับตัวอยู่รึเปล่าอะตอนนั้นมันทำให้ฉันตกใจมากเลยนะแต่ว่าเธอไปเรียนที่จะเล่นมันมากับใครหรอยังไงก็เถอะ#เธอทำให้ฉันตะลึงจริงๆเลยนะเนี่ยถึงว่าทำไมฉันถึงชอบเธอได้ขนาดนี้!$h",
                "Rainy_Day_3": "#$c .5#ฉันไปฝึกฟันดาบกลางสายฝนมาน่ะอิอิเธอต้องภูมิใจนะว่าเพื่อนเธอน่ะเจ๋งที่สุด$h#อาจจะเป็นวันที่ดีในการลงเหมืองนะแต่ว่าระวังตัวหน่อยล่ะบางทีพกยาไปสักขวดสองขวดก็ดีนะ",
                "Rainy_Night_1": "#$c .5#ตอนกลางคืนแบบนี้มันเหมาะมากเลยนะที่ได้เจอผี...#นี่!เธอดูเหนื่อยๆนะให้ฉันทำอะไรให้กินมั้ย?",
                "Indoor_Day_4": "#$c .5#วันนี้ฉันจะทำความสะอาดบ้านหน่อยล่ะนะเพราะว่างานในฟามเธอคงหนักน่าดูถึงแม้ว่ามันจะเป็นสิ่งที่ฉันช่วยทำได้แค่นี้ก็เถอะ#เธอจะว่าอะไรมั้ย?ถ้าฉันจะจัดห้องใหม่นิดหน่อย",
                "Indoor_Night_0": "#$c .5#นี่ๆเธอดูดีมากเลยนะวันนี้มีเคล็ดลับอะไรหรอบอกฉันหน่อยสิ$l#วันนี้ฉันรู้สึกดีสุดๆไปเลยถ้าเธอลองดูดีๆเธอจะเห็นว่าสิ่งรอบตัวมันน่าทึ่งแค่ไหน",
                "Outdoor_0": "#$c .5#ว้าวเป็นเช้าที่สดใสสุดๆไปเลยนะเนี่ยฉันพลาดอะไรดีๆไปเยอะเลยนะเนี่ยก่อนจะที่จะมาเป็น{{RelationshipLabel}}$h#สายลมเย็นๆคอยพัดพากลิ่นต้นสนอ่อนๆมาที่หุบเขาที่นี่",
                "TwoKids_3": "#$c .5#เรารับเลี้ยงเด็กๆมาเร็วไปมั้ยเนี่ยแต่มองในแง่ดีนะเราจะได้ไม่แก่เกินไปตอนที่เด็กๆโตกันแล้ว#มีทั้งบ้านสุดเจ๋งกับเด็กๆที่น่ารักและก็ฟาร์มที่เจ๋งเหมือนกันฉันไม่นึกเลยนะว่าชีวิตจะมีอะไรดีๆแบบนี้ได้แต่อันนี้ก็แค่เริ่มต้นล่ะ$h",
                "spring_16": "เธอจะว่าอะไรฉันมั้ยถ้าเกิดวันนี้ฉันจะเล่นเกมทั้งวัน..?#$b#แต่ก็นะ...มันก็ฟังดูน่าสนุกดีน่ะ$h",
                "summer_23": "เพื่อนๆทางออนไลน์ของฉันตกใจกันมากเลยล่ะพอรู้ว่าพวกเราเป็น{{RelationshipLabel}} ",
                "winter_19": "คืนนี้จะเป็นคืนที่ทุกๆคนมาสังสรรค์กันฉันหวังว่าเธอจะมาจอยกันนะ?#$e#ได้เจอกับกลุ่มเพื่อนก็เป็นอะไรที่ดีนะ$h",
            },
            "When":
            {
                "UseLovePortraits": true,
                "HasMod |contains=gizzymo.canonfriendlyexpansion": "true"
            },
        },
        {
            "Action": "EditData",
            "Target": "Characters/Dialogue/MarriageDialogueAbigail",
            "Entries":
            {
                "Rainy_Day_0": "#$c .5#ฉันว่าวันนี้จะเอาสมุดสเก็ตช์ออกมาปัดฝุ่นหน่อยละนะเพราะพึ่งได้ไอเดียสัตว์ในเทพนิยายมา#ความมืด... สายฝน... มันทำให้ฉันตื่นเต้นอย่างบอกไม่ถูกเลยละ$h",
                "Rainy_Day_1": "นี่ๆจำตอนนั้นได้มั้ยตอนที่ฝนตกลงมาแล้วเราก็เล่นเพลงด้วยกันพอฝนตกแบบนี้ก็ทำให้ย้อนคิดขึ้นมาน่ะ#$e#$c .5#เธอยังพกพิณอยู่กับตัวอยู่รึเปล่าอะตอนนั้นมันทำให้ฉันตกใจมากเลยนะแต่ว่าเธอไปเรียนที่จะเล่นมันมากับใครหรอยังไงก็เถอะ#เธอทำให้ฉันตะลึงจริงๆเลยนะเนี่ยถึงว่าทำไมฉันถึงชอบเธอได้ขนาดนี้!$h",
                "Rainy_Day_3": "#$c .5#ฉันไปฝึกฟันดาบกลางสายฝนมาน่ะอิอิเธอต้องภูมิใจนะว่าเพื่อนเธอน่ะเจ๋งที่สุด$h#อาจจะเป็นวันที่ดีในการลงเหมืองนะแต่ว่าระวังตัวหน่อยล่ะบางทีพกยาไปสักขวดสองขวดก็ดีนะ",
                "Rainy_Night_1": "#$c .5#ตอนกลางคืนแบบนี้มันเหมาะมากเลยนะที่ได้เจอผี...#นี่!เธอดูเหนื่อยๆนะให้ฉันทำอะไรให้กินมั้ย?",
                "Indoor_Day_4": "#$c .5#วันนี้ฉันจะทำความสะอาดบ้านหน่อยล่ะนะเพราะว่างานในฟามเธอคงหนักน่าดูถึงแม้ว่ามันจะเป็นสิ่งที่ฉันช่วยทำได้แค่นี้ก็เถอะ#เธอจะว่าอะไรมั้ย?ถ้าฉันจะจัดห้องใหม่นิดหน่อย",
                "Indoor_Night_0": "#$c .5#นี่ๆเธอดูดีมากเลยนะวันนี้มีเคล็ดลับอะไรหรอบอกฉันหน่อยสิ$l#วันนี้ฉันรู้สึกดีสุดๆไปเลยถ้าเธอลองดูดีๆเธอจะเห็นว่าสิ่งรอบตัวมันน่าทึ่งแค่ไหน",
                "Outdoor_0": "#$c .5#ว้าวเป็นเช้าที่สดใสสุดๆไปเลยนะเนี่ยฉันพลาดอะไรดีๆไปเยอะเลยนะเนี่ยก่อนจะที่จะมาเป็น{{RelationshipLabel}}$h#สายลมเย็นๆคอยพัดพากลิ่นต้นสนอ่อนๆมาที่หุบเขาที่นี่",
                "TwoKids_3": "#$c .5#เรารับเลี้ยงเด็กๆมาเร็วไปมั้ยเนี่ยแต่มองในแง่ดีนะเราจะได้ไม่แก่เกินไปตอนที่เด็กๆโตกันแล้ว#มีทั้งบ้านสุดเจ๋งกับเด็กๆที่น่ารักและก็ฟาร์มที่เจ๋งเหมือนกันฉันไม่นึกเลยนะว่าชีวิตจะมีอะไรดีๆแบบนี้ได้แต่อันนี้ก็แค่เริ่มต้นล่ะ$h",
                "spring_16": "เธอจะว่าอะไรฉันมั้ยถ้าเกิดวันนี้ฉันจะเล่นเกมทั้งวัน..?#$b#แต่ก็นะ...มันก็ฟังดูน่าสนุกดีน่ะ$h",
                "summer_23": "เพื่อนๆทางออนไลน์ของฉันตกใจกันมากเลยล่ะพอรู้ว่าพวกเราเป็น{{RelationshipLabel}} ",
                "winter_19": "คืนนี้จะเป็นคืนที่ทุกๆคนมาสังสรรค์กันฉันหวังว่าเธอจะมาจอยกันนะ?#$e#ได้เจอกับกลุ่มเพื่อนก็เป็นอะไรที่ดีนะ$h",
                "summer_22": "โอย... เมื่อคืนนอนไม่ค่อยหลับเลยแถมหลังก็ปวดมากๆด้วยฉันว่าวันนี้ฉันคงทำอะไรไม่ได้เลย...$s#$e#...แต่ฉันจะพยายามละกันนะ#$e#ฉันรู้นะว่ามันพึ่งผ่านมาไม่นานตอนที่ฉันพึ่งเจอกับเธอแต่ตอนนี้ฉันก็ยังทำตัวเป็นผ฿้ใหญ่ไม่ได้สักที$s#$b#ฉันรู้สึกว่าตัวเองโตขึ้นเยอะนะแต่ว่าก็ยังไม่เท่าพ่อแม่ฉันเลย$u#$e#ใครจะไปรู้ละว่าการโตเป็นผู้ใหญ่มันจะน่ากลัวพอๆกับไปบุกเหมือง$h#$b#แต่ฉันดีใจนะที่มีเธออยู่ข้างๆ",
            },
            "When":
            {
                "UseLovePortraits": false,
                "HasMod |contains=gizzymo.canonfriendlyexpansion": "true"
            },
        },
        {
            "Action": "EditData",
            "Target": "Characters/Dialogue/MarriageDialogueAbigail",
            "Entries":
            {
                "Indoor_Night_1": "#$c .5#รอไม่ไหวแล้วที่จะไปซุกตัวใต้ผ้าห่มไฟฟ้า#ว่าแต่บอกฉันหน่อยสิว่าวันนี้มีอะไรน่าสนใจเกินขึ้นมั้ย?$h",
            },
            "When":
            {
                "EnableAsexuality": "true",
                "HasMod |contains=gizzymo.canonfriendlyexpansion": "true"
            },
        },
        {
            "Action": "EditData",
            "Target": "Characters/Dialogue/Pierre",
            "Entries":
            {
                "fall_Mon_inlaw_Abigail": "สวัสดี @ เดี๋ยวนี้เป็นไงบ้าง?",
                "winter_Mon_inlaw_Abigail": "สวัสดี @ เดี๋ยวนี้เป็นไงบ้าง?",
            },
        },
        //COMPATIBILITY: SPOUSES REACT TO PLAYER 'DEATH' v1.1.0
        //Lines in this section are based on the original lines written by CasualInvidia, used and edited with permission. (Thank you, CasualInvidia!)
    {       //Mine death with Abigail
	        "LogName": "KO Mines- Abigail",
            "Action": "EditData",
            "Target": "Data/Events/Mine",
            "Entries": {
                "PlayerKilled": "none/-100 -100/farmer 20 10 2 {{Spouse}} 19 10 1 Marlon 18 10 3/skippable/pause 1500/showFrame 5/message \" ...{2}?\"/pause 1000/message \" {{TermofEndearment}}, ตื่นเร็ว!\"/viewport 19 10 true/pause 1500/speak {{Spouse}} \"อ้ะ! ตื่นแล้วนิ!\"/pause 500/emote farmer 40/pause 500/faceDirection farmer 1/faceDirection farmer 3/pause 500/emote farmer 8/pause 1000/speak {{Spouse}} \"แปลกมากๆเลยอะตอนนั้นฉันรู้สึกถึงอะไรไม่ดีและฉันก็รู้ทันทีเลยว่าต้องเป็นเธอแน่นอน#$b#ไม่ต้องถามนะว่ารู้ได้ไงแค่อยู่ดีๆมันก็แว้บเข้ามา#$b#แต่ไม่ว่ามันคืออะไรก็คงเป็นอะไรดีๆละนะเพราะว่ามันพาให้มาเจอเธอ\"/pause 1000/speak Marlon \และฉันก็เลยมากับอบิเกลเพื่อเคลีย์ทางให้น่ะ#$b#ตอนแรกฉันก็อยู่คนเดียวนะแต่อบิเกลขอฉันร่วมเดินทางมาด้วย#$b#เธอโชคดีนะที่มีคนแบบอบิเกลเป็นเพื่อน\"/emote {{Spouse}} 16/pause 500/speak {{Spouse}} \"แบบที่กล้าหาญอะหรอฉันชอบนะเหมือนนายกำลังจะชวนฉันไปอยู่กิลด์ด้วยเลย.$4\"/pause 1000/speak Marlon \"เปล่าหรอกฉันแค่เห็นอะไรก็พูดไปงั้นเพราะว่าเธอกล้าหาญจริงๆ\"/pause 500/move Marlon 0 0 1/pause 500/faceDirection Marlon 3/speak Marlon \"แต่ตอนนี้มันสมควรออกจากที่นี่ได้แล้วล่ะ @ ต้องพักสักหน่อยนะเอาล่ะรีบไปได้แล้ว\"/pause 500/textAboveHead Marlon \"ลาก่อน\"/move Marlon 0 4 0/warp Marlon -100 -100/pause 1500/speak {{Spouse}} \นี่ @...รู้มั้ยฉันเป็นห่วงเธอมากๆเลยนะ.#$b#ตอนฉันลงไปที่เหมืองฉันไม่ค่อยสนุกเลยพอคิดอย่างเดียวว่าเธอกำลังตกอยู่ในอันตราย$2#$b#ฉันดีใจมากๆเลยที่มาช่วยเธอได้ทัน#$b#รอฉันก่อนนะจนถึงวันนั้นไว้เราไปผจญภัยด้วยกันนะ!$1\"/pause 500/emote farmer 20/faceDirection farmer 2/showFrame 0/pause 500/minedeath/end dialogue {{Spouse}} \"นี่ๆฉันพึ่งซ้อมฟันดาบเสร็จน่ะคราวหลังตอนเธอไปลงเหมือนเราจะได้ไปด้วยกันแล้วนะ!$1#$c 0.7#แต่ว่าคงไม่เร็วไปหรอกนะฉันคงต้องฝึกให้เยอะกว่านี้แล้ว$1#$b#ฉันกำลังจะพักกินขนมอยู่พอดีมากินด้วยกันมั้ยละ[210 215 223 228 232 243 403 406 613 618 636 651]$1\"",
    		},
		    "When": {
		        "Spouse": "Abigail",
			"HasMod |contains=CasualInvidia.SpousesReactToDeath": "true"
		    }
	     },
    {       //Hospital Death- Abigail
            "LogName": "Player 'Killed'- Abigail",
            "Action": "EditData",
            "Target": "Data/Events/Hospital",
            "Entries": {
                "PlayerKilled": "none/-100 -100/farmer 20 12 2 Harvey 21 12 3 {{Spouse}} 22 8 2/skippable/pause 1500/showFrame 5/message \"...{0}?\"/pause 1000/message \"เอาล่ะค่อยๆลืมตานะ\"/viewport 20 12 true/pause 1000/speak Harvey \"ไง @ ฉันดีใจนะที่คุณตื่นขึ้นมา#$b#มีคนพาคุณมาที่นี่ตอนนั้นสภาพคุณดูไม่ได้เลยล่ะฉันต้องพาคุณเข้ารับการผ่าตัดด่วนเลยด้วย!\"/speed {{Spouse}} 5/move {{Spouse}} 0 3 2/textAboveHead {{Spouse}} \"{0}!\"/emote farmer 16/move {{Spouse}} -1 0 2/faceDirection farmer 1/move Harvey 1 0 3/move {{Spouse}} 0 1 3/speak {{Spouse}} \"โอ้พระเจ้าค่อยๆลุกนะ$2\"/emote farmer 60/pause 500/speak {{Spouse}} \"ฉันดีใจจริงๆที่เธอดูดีขึ้นหมอฮาร์วีย์คงรักษาเธออย่างสุดความสามารถเลยสินะ#$b#ตอนที่ฉันรออยู่ข้างนอกฉันกระวนการวายใจมากๆเลยล่ะ...$2\"/emote {{Spouse}} 40/pause 1500/emote farmer 28/pause 500/pause 500/speak Harvey \"ตอนนี้อาการคุณดีขึ้นมากแล้วนะครับ @ แต่คราวหลังต้องระวังตัวมากกว่านี้นะครับ$2\"/pause 500/speak Harvey \"ผมจะให้ทั้งคู่คุยกันเป็นการส่วนตัวนะครับ\"/pause 500/move Harvey 0 -4 0/move Harvey -8 0 0 true/move Harvey 0 -1 0/move Harvey -4 0 0/move Harvey 0 -1 0/playSound doorClose/warp Harvey -100 -100/pause 500/faceDirection {{Spouse}} 3/speak {{Spouse}} \" @ รู้มั้ย... ตอนนี้ฉันก็ยังฝึกซ้อมดาบให้เก่งพอๆกับเธออยู่นะ#$b#สักวันฉันจะยืนเคียงข้างเธอและจะปกป้องเธอให้ได้เลย#$b#จนถึงตอนนั้นอย่าจากฉันไปไหนก่อนนะ$2\"/faceDirection farmer 2/pause 1000/emote farmer 28/hospitaldeath/end dialogue {{Spouse}} \"เอาล่ะนั่งตรงนี้และผักผ่อนไปนะฉันจะดูแลเธอจนกว่าเธอจะกลับมาดีขึ้น#$c 0.7#... ฉันจะต้องฝคกซ้อมให้มากกว่านี้เพื่อที่จะไปป้องเธอให้ได้ {{Lowercase:{{TermofEndearment}}}}.$2#$b#ฉันเอานี่มาให้ด้วยขอให้ดีขึ้นเร็วๆนะ [237 241 203 204 220 244]\"",
            },
            "When": {
		        "Spouse": "Abigail",
			"Relationship:Harvey |contains=Married": "false",
			"Relationship:Maru |contains=Married": "false",
                	"TermofEndearment |contains=@": "false",
                	"TermofEndearment |contains=BFF": "false",
			"HasMod |contains=CasualInvidia.SpousesReactToDeath": "true"
            },
         },
    {       //Hospital Death- Abigail
            "LogName": "Player 'Killed'- Abigail",
            "Action": "EditData",
            "Target": "Data/Events/Hospital",
            "Entries": {
                "PlayerKilled": "none/-100 -100/farmer 20 12 2 Harvey 21 12 3 {{Spouse}} 22 8 2/skippable/pause 1500/showFrame 5/message \"...{0}?\"/pause 1000/message \"เอาล่ะค่อยๆลืมตานะ\"/viewport 20 12 true/pause 1000/speak Harvey \"ไง @ ฉันดีใจนะที่คุณตื่นขึ้นมา#$b#มีคนพาคุณมาที่นี่ตอนนั้นสภาพคุณดูไม่ได้เลยล่ะฉันต้องพาคุณเข้ารับการผ่าตัดด่วนเลยด้วย!\"/speed {{Spouse}} 5/move {{Spouse}} 0 3 2/textAboveHead {{Spouse}} \"{0}!\"/emote farmer 16/move {{Spouse}} -1 0 2/faceDirection farmer 1/move Harvey 1 0 3/move {{Spouse}} 0 1 3/speak {{Spouse}} \"โอ้พระเจ้าค่อยๆลุกนะ$2\"/emote farmer 60/pause 500/speak {{Spouse}} \"ฉันดีใจจริงๆที่เธอดูดีขึ้นหมอฮาร์วีย์คงรักษาเธออย่างสุดความสามารถเลยสินะ#$b#ตอนที่ฉันรออยู่ข้างนอกฉันกระวนการวายใจมากๆเลยล่ะ...$2\"/emote {{Spouse}} 40/pause 1500/emote farmer 28/pause 500/pause 500/speak Harvey \"ตอนนี้อาการคุณดีขึ้นมากแล้วนะครับ @ แต่คราวหลังต้องระวังตัวมากกว่านี้นะครับ$2\"/pause 500/speak Harvey \"ผมจะให้ทั้งคู่คุยกันเป็นการส่วนตัวนะครับ\"/pause 500/move Harvey 0 -4 0/move Harvey -8 0 0 true/move Harvey 0 -1 0/move Harvey -4 0 0/move Harvey 0 -1 0/playSound doorClose/warp Harvey -100 -100/pause 500/faceDirection {{Spouse}} 3/speak {{Spouse}} \"@ รู้มั้ย... ตอนนี้ฉันก็ยังฝึกซ้อมดาบให้เก่งพอๆกับเธออยู่นะ#$b#สักวันฉันจะยืนเคียงข้างเธอและจะปกป้องเธอให้ได้เลย#$b#จนถึงตอนนั้นอย่าจากฉันไปไหนก่อนน$2\"/faceDirection farmer 2/pause 1000/emote farmer 28/hospitaldeath/end dialogue {{Spouse}} \"เอาล่ะนั่งตรงนี้และผักผ่อนไปนะฉันจะดูแลเธอจนกว่าเธอจะกลับมาดีขึ้น#$c 0.7#... ฉันจะต้องฝคกซ้อมให้มากกว่านี้เพื่อที่จะไปป้องเธอให้ได้ {{Lowercase:{{TermofEndearment}}}}.$2#$b#ฉันเอานี่มาให้ด้วยขอให้ดีขึ้นเร็วๆนะ [237 241 203 204 220 244]\"",
            },
            "When": {
		        "Spouse": "Abigail",
			"Relationship:Harvey |contains=Married": "false",
			"Relationship:Maru |contains=Married": "false",
			"TermofEndearment": "@, BFF",
			"HasMod |contains=CasualInvidia.SpousesReactToDeath": "true"
            },
         },
     {       //Island death after Leo
	        "LogName": "Island Death- LeoMoved, Abigail",
            "Action": "EditData",
            "Target": "Data/Events/IslandSouth",
            "Entries": {
                "PlayerKilled": "none/-100 -100/farmer 13 33 2 Willy 15 33 3/pause 1500/showFrame 5/message \" ...{2}?\"/pause 1000/message \" {2}, ตื่นเร็ว!\"/viewport 13 33 clamp true/pause 1000/speak Willy \"เธอเป็นอะไรมั้ย?ฉันเห็นเธอนอนหน้าคว่ำอยู่ในทรายนึกว่าจะเกิดอะไรไม่ดีสะอีก\"/emote farmer 16/faceDirection farmer 1/pause 500/speak Willy \"เธอควรจะระวังตัวหน่อยนะเวลาเข้าไปที่ภูเขาไฟนั่น#$b#เจ้าหนูลีโอก็ย้ายไปที่เมืองเราแล้วก็จะไม่มีใครมาเจอเธอแบบนี้นะเธอโชคดีที่มีชั้นอยู่#$b#เสื้อเธอเละไปหมดเลยแฮะหวังว่าตอนกลับไปเธอจะไม่ทำให้ {{SocialMenuLabel}} ตกใจนะ$1\"/faceDirection farmer 2/showFrame 0/pause 1000/emote farmer 28/minedeath/end dialogue {{Spouse}} \"ตายแล้ว @ เธอไปโดนอะไรมาน่ะ!$7#$b#ขอโทษนะที่สติแตกแต่ว่าเธอสภาพดูไม่จืดเลย...$2#$b#แต่เธอไม่เป็นไรก็ดีแล้วล่ะ$6#$b#ในวันที่ฉันเก่งพอฉันจะไปผจญภัยกับเธอแล้วก็ให้พวกมอนเตอร์พวกนั้นกลัวหัวหดไปเลย\"",
   		    },
		    "When": {
		        "HasFlag": "leoMoved",
                	"Spouse": "Abigail",
			"Relationship:Willy |contains=Married": "false",
                	"HasMod |contains=CasualInvidia.SpousesReactToDeath": "true"
		    }
	     },
       //Hospital Death- Abigail Ex and Island Death - Abigail before/with Leo: no changes needed
	//
        //COMPATIBILITY IMMERSIVE SPOUSES - IMPROVED SPOUSE SCHEDULES v0.5-beta
        //Lines in this section are based on the original lines written by yeet (Someguy363), used and edited with permission. (Thank you, yeet!)
	{
		"Action": "EditData",
		"Target": "Strings/schedules/Abigail",
		"Entries": {
			"marriage_bus4": "อยากมาใช้เวลาด้วยกันสักหน่อยมั้ย @?#$b#{{Random: รู้แล้วๆขอฉันอ่านลายมือเธอหน่อยละกันนะ$h, เอเอาเป็นมาชมฉันดีกว่านะ?}}",
			"marriage_forest": "พ่อฉันจะต้องสติแตกแน่เลยถ้ารู้ว่าฉันมาที่นี่#$b#อยู่ที่นี่แล้วรู้สึกมีชีวิตชีวาที่สุดเลย$l",
			"marriage_13": "พวกเขาบอกว่าฉันมาได้แต่ต้องมากับเธอเท่านั้น$9#$b#ฉันรู้สึกตะหงิดใจมากเพราะเดี๋ยวนี้เค้าให้เด็กๆเข้าไปเดินดูตอนพวกเค้าซ่อนไข่ได้#$b#ฉันว่าคู่ {{RelationshipLabel}}หลายคนๆน่าจะทำแบบนั้นกัน$h",
			"marriage_16": "ไปด้วยกันเถอะฉันอยากให้พ่อเห็นว่าฉันพาใครมา$h",
			},
		    "When": {
			"UseLovePortraits": "true",
                	"HasMod |contains=iss.immersivespouses": "true"
		    }
		},
	{
		"Action": "EditData",
		"Target": "Strings/schedules/Abigail",
		"Entries": {
			"marriage_bus4": "อยากมาใช้เวลาด้วยกันสักหน่อยมั้ย @?#$b#{{Random: รู้แล้วๆขอฉันอ่านลายมือเธอหน่อยละกันนะ$h, เอเอาเป็นมาชมฉันดีกว่านะ?}}",
			"marriage_forest": "พ่อฉันจะต้องสติแตกแน่เลยถ้ารู้ว่าฉันมาที่นี่#$b#อยู่ที่นี่แล้วรู้สึกมีชีวิตชีวาที่สุดเลย$l",
			"marriage_13": "พวกเขาบอกว่าฉันมาได้แต่ต้องมากับเธอเท่านั้น$9#$b#ฉันรู้สึกตะหงิดใจมากเพราะเดี๋ยวนี้เค้าให้เด็กๆเข้าไปเดินดูตอนพวกเค้าซ่อนไข่ได้#$b#ฉันว่าคู่ {{RelationshipLabel}}หลายคนๆน่าจะทำแบบนั้นกัน$h",
			"marriage_16": "ไปด้วยกันเถอะฉันอยากให้พ่อเห็นว่าฉันพาใครมา$h",
			},
		    "When": {
			"UseLovePortraits": "false",
                	"HasMod |contains=iss.immersivespouses": "true"
		    }
		},
	{
		"Action": "EditData",
		"Target": "Strings/schedules/Abigail",
		"Entries": {
			"marriage_forest2": เธอคิดว่าถ้าฉันกรี้ดออกมาดังๆตาลุงที่ยอู่บนหอคอยนั่นจะออกมาดูมั้ย?#$b#แต่เอาจริงๆฉันคงไม่ต้องการความช่วยจากตาลุงนั่นหรอก!$h",
			},
		    "When": {
			"EnableAsexuality": "true",
                	"HasMod |contains=iss.immersivespouses": "true"
		    }
		},
	{
		"Action": "EditData",
		"Target": "Characters/Dialogue/MarriageDialogueAbigail",
		"Entries": {
			"spring_4": "โอ้ไง {{TermofEndearment}} ถ้าต้องการอะไรก็มาหาที่คลินิกได้นะ"
		},
		    "When": {
                	"HasMod |contains=iss.immersivespouses": "true"
		    }
	},
    ]
}
